jobbergate_api/__init__.py
jobbergate_api/apps/__init__.py
jobbergate_api/apps/clusters/__init__.py
jobbergate_api/apps/clusters/models.py
jobbergate_api/apps/clusters/routers.py
jobbergate_api/apps/clusters/schemas.py
jobbergate_api/apps/constants.py
jobbergate_api/apps/dependencies.py
jobbergate_api/apps/file_validation.py
jobbergate_api/apps/garbage_collector.py
jobbergate_api/apps/job_script_templates/__init__.py
jobbergate_api/apps/job_script_templates/constants.py
jobbergate_api/apps/job_script_templates/models.py
jobbergate_api/apps/job_script_templates/routers.py
jobbergate_api/apps/job_script_templates/schemas.py
jobbergate_api/apps/job_script_templates/services.py
jobbergate_api/apps/job_script_templates/tools.py
jobbergate_api/apps/job_scripts/__init__.py
jobbergate_api/apps/job_scripts/models.py
jobbergate_api/apps/job_scripts/routers.py
jobbergate_api/apps/job_scripts/schemas.py
jobbergate_api/apps/job_scripts/services.py
jobbergate_api/apps/job_scripts/tools.py
jobbergate_api/apps/job_submissions/__init__.py
jobbergate_api/apps/job_submissions/constants.py
jobbergate_api/apps/job_submissions/helpers.py
jobbergate_api/apps/job_submissions/models.py
jobbergate_api/apps/job_submissions/routers.py
jobbergate_api/apps/job_submissions/schemas.py
jobbergate_api/apps/job_submissions/services.py
jobbergate_api/apps/models.py
jobbergate_api/apps/permissions.py
jobbergate_api/apps/protocols.py
jobbergate_api/apps/schemas.py
jobbergate_api/apps/services.py
jobbergate_api/config.py
jobbergate_api/email_notification.py
jobbergate_api/logging.py
jobbergate_api/main.py
jobbergate_api/meta_mapper.py
jobbergate_api/rabbitmq_notification.py
jobbergate_api/safe_types.py
jobbergate_api/security.py
jobbergate_api/storage.py
jobbergate_api/utils/cron.py
jobbergate_api/version.py
jobbergate_api-5.9.0.dist-info/LICENSE
jobbergate_api-5.9.0.dist-info/METADATA
jobbergate_api-5.9.0.dist-info/WHEEL
jobbergate_api-5.9.0.dist-info/entry_points.txt
jobbergate_api-5.9.0.dist-info/RECORD
